markdiffusion/README.md
markdiffusion/__init__.py
markdiffusion/config/GM.json
markdiffusion/config/GS.json
markdiffusion/config/PRC.json
markdiffusion/config/RI.json
markdiffusion/config/ROBIN.json
markdiffusion/config/SEAL.json
markdiffusion/config/SFW.json
markdiffusion/config/TR.json
markdiffusion/config/VideoMark.json
markdiffusion/config/VideoShield.json
markdiffusion/config/WIND.json
markdiffusion/config/__init__.py
markdiffusion/dataset/__init__.py
markdiffusion/dataset/mscoco/__init__.py
markdiffusion/dataset/mscoco/mscoco.parquet
markdiffusion/dataset/stable_diffusion_prompts/data/eval.parquet
markdiffusion/dataset/stable_diffusion_prompts/data/train.parquet
markdiffusion/dataset/vbench/__init__.py
markdiffusion/dataset/vbench/prompts_per_dimension/__init__.py
markdiffusion/dataset/vbench/prompts_per_dimension/appearance_style.txt
markdiffusion/dataset/vbench/prompts_per_dimension/color.txt
markdiffusion/dataset/vbench/prompts_per_dimension/human_action.txt
markdiffusion/dataset/vbench/prompts_per_dimension/multiple_objects.txt
markdiffusion/dataset/vbench/prompts_per_dimension/object_class.txt
markdiffusion/dataset/vbench/prompts_per_dimension/overall_consistency.txt
markdiffusion/dataset/vbench/prompts_per_dimension/scene.txt
markdiffusion/dataset/vbench/prompts_per_dimension/spatial_relationship.txt
markdiffusion/dataset/vbench/prompts_per_dimension/subject_consistency.txt
markdiffusion/dataset/vbench/prompts_per_dimension/temporal_flickering.txt
markdiffusion/dataset/vbench/prompts_per_dimension/temporal_style.txt
markdiffusion/detection/__init__.py
markdiffusion/detection/base.py
markdiffusion/detection/gm/gm_detection.py
markdiffusion/detection/gs/gs_detection.py
markdiffusion/detection/prc/prc_detection.py
markdiffusion/detection/ri/ri_detection.py
markdiffusion/detection/robin/robin_detection.py
markdiffusion/detection/seal/seal_detection.py
markdiffusion/detection/sfw/sfw_detection.py
markdiffusion/detection/tr/tr_detection.py
markdiffusion-1.0.1.post1.dist-info/licenses/LICENSE
markdiffusion-1.0.1.post1.dist-info/METADATA
markdiffusion-1.0.1.post1.dist-info/WHEEL
markdiffusion-1.0.1.post1.dist-info/top_level.txt
markdiffusion-1.0.1.post1.dist-info/RECORD
