Metadata-Version: 2.4
Name: markdiffusion
Version: 1.0.1.post1
Summary: An Open-Source Toolkit for Generative Watermarking of Latent Diffusion Models
Author-email: Leyi Pan <panly24@mails.tsinghua.edu.cn>, Sheng Guan <guansheng2022@bupt.edu.cn>, Zheyu Fu <fuzheyu23@mails.tsinghua.edu.cn>, Luyang Si <sily23@mails.tsinghua.edu.cn>, Huan Wang <huan-wan23@mails.tsinghua.edu.cn>, Zian Wang <authurwzaa@gmail.com>, Hanqian Li <hli994@connect.hkust-gz.edu.cn>, Xuming Hu <xuminghu97@gmail.com>, Irwin King <king@cuhk.edu.cn>, "Philip S.Yu" <psyu@uic.edu>, Aiwei Liu <liuaiwei20@gmail.com>, Lijie Wen <wenlj@tsinghua.edu.cn>
Maintainer-email: Leyi Pan <panly24@mails.tsinghua.edu.cn>, Sheng Guan <codelformat@gmail.com>
License: Apache-2.0
Project-URL: Homepage, https://generative-watermark.github.io/
Project-URL: Documentation, https://markdiffusion.readthedocs.io/
Project-URL: Repository, https://github.com/THU-BPM/markdiffusion
Project-URL: Issues, https://github.com/THU-BPM/markdiffusion/issues
Project-URL: Changelog, https://github.com/THU-BPM/markdiffusion/releases
Keywords: watermark,diffusion,generative-ai,stable-diffusion,video-generation,trustworthy-ai,ai-safety,deep-learning,pytorch
Classifier: Development Status :: 4 - Beta
Classifier: Intended Audience :: Developers
Classifier: Intended Audience :: Science/Research
Classifier: License :: OSI Approved :: Apache Software License
Classifier: Operating System :: OS Independent
Classifier: Programming Language :: Python :: 3
Classifier: Programming Language :: Python :: 3.10
Classifier: Programming Language :: Python :: 3.11
Classifier: Programming Language :: Python :: 3.12
Classifier: Topic :: Scientific/Engineering :: Artificial Intelligence
Classifier: Topic :: Scientific/Engineering :: Image Processing
Classifier: Topic :: Security
Requires-Python: >=3.10
License-File: LICENSE
Requires-Dist: numpy>=1.20
Requires-Dist: Pillow>=8.0
Requires-Dist: opencv-python>=4.10
Requires-Dist: requests>=2.26
Requires-Dist: tqdm>=4.60
Requires-Dist: scipy>=1.7
Requires-Dist: matplotlib>=3.4
Requires-Dist: diffusers>=0.25
Requires-Dist: transformers>=4.30
Requires-Dist: accelerate>=0.20
Requires-Dist: huggingface_hub>=0.16
Requires-Dist: ujson>=5.10.0
Requires-Dist: datasets>=2.0
Requires-Dist: sentence-transformers>=5.0.0
Requires-Dist: joblib>=1.5.1
Requires-Dist: pandas>=1.4
Requires-Dist: pycryptodome>=3.23
Provides-Extra: optional
Requires-Dist: ldpc>=2.3.8; extra == "optional"
Requires-Dist: lpips>=0.1.4; extra == "optional"
Requires-Dist: piq>=0.7; extra == "optional"
Requires-Dist: pyiqa>=0.1.7; extra == "optional"
Requires-Dist: timm>=0.9; extra == "optional"
Requires-Dist: easydict>=1.9; extra == "optional"
Requires-Dist: galois>=0.4.7; extra == "optional"
Requires-Dist: Levenshtein>=0.27.1; extra == "optional"
Requires-Dist: qrcode>=7.4.2; extra == "optional"
Provides-Extra: test
Requires-Dist: pytest>=7.0; extra == "test"
Requires-Dist: pytest-cov>=4.0; extra == "test"
Provides-Extra: dev
Requires-Dist: pytest>=7.0; extra == "dev"
Requires-Dist: pytest-cov>=4.0; extra == "dev"
Requires-Dist: black>=23.0; extra == "dev"
Requires-Dist: isort>=5.12; extra == "dev"
Requires-Dist: flake8>=6.0; extra == "dev"
Requires-Dist: mypy>=1.0; extra == "dev"
Requires-Dist: pre-commit>=3.0; extra == "dev"
Provides-Extra: docs
Requires-Dist: sphinx>=6.0; extra == "docs"
Requires-Dist: sphinx-rtd-theme>=1.2; extra == "docs"
Requires-Dist: myst-parser>=1.0; extra == "docs"
Dynamic: license-file
